mysgen/mysgen.py
mysgen-0.4.4.dist-info/LICENSE
mysgen-0.4.4.dist-info/METADATA
mysgen-0.4.4.dist-info/WHEEL
mysgen-0.4.4.dist-info/top_level.txt
mysgen-0.4.4.dist-info/RECORD
