Metadata-Version: 2.1
Name: mysgen
Version: 0.4.4
Summary: My simple static site generator.
Author-email: Mladen Gibanica <11275336+mgcth@users.noreply.github.com>
License: MIT
Requires-Python: >=3.8
License-File: LICENSE
Requires-Dist: Markdown ~=3.3
Requires-Dist: Pillow ~=10.1
Requires-Dist: jinja2 ~=2.11.3
Requires-Dist: python-markdown-math ~=0.8
Requires-Dist: MarkupSafe ==1.1.1
Requires-Dist: boto3 ~=1.26
Requires-Dist: pillow-avif-plugin ~=1.4
Provides-Extra: dev
Requires-Dist: mysgen[lint] ; extra == 'dev'
Requires-Dist: mysgen[type] ; extra == 'dev'
Requires-Dist: mysgen[test] ; extra == 'dev'
Requires-Dist: pre-commit ~=2.20 ; extra == 'dev'
Provides-Extra: lint
Requires-Dist: ruff ~=0.1 ; extra == 'lint'
Provides-Extra: test
Requires-Dist: pytest ~=7.1 ; extra == 'test'
Requires-Dist: coverage ~=6.5 ; extra == 'test'
Requires-Dist: pytest-cov ~=4.0 ; extra == 'test'
Provides-Extra: type
Requires-Dist: mypy ~=1.7 ; extra == 'type'
Requires-Dist: boto3-stubs ~=1.29 ; extra == 'type'
Requires-Dist: types-Jinja2 ~=2.11 ; extra == 'type'
Requires-Dist: types-Markdown ~=3.5 ; extra == 'type'
Requires-Dist: types-Pillow ~=10.1 ; extra == 'type'
